calendly/__init__.py
calendly/activity_log.py
calendly/availability.py
calendly/data_compliance.py
calendly/event_types.py
calendly/organizations.py
calendly/routing_forms.py
calendly/scheduled_events.py
calendly/scheduling_links.py
calendly/sdk.py
calendly/shares.py
calendly/users.py
calendly/webhooks.py
calendly/models/__init__.py
calendly/models/operations/__init__.py
calendly/models/operations/delete_organizations_uuid_memberships.py
calendly/models/operations/delete_users_user_uuid_webhooks_webhook_uuid.py
calendly/models/operations/deleteinviteenoshow.py
calendly/models/operations/get_event_types_uuid.py
calendly/models/operations/get_organizations_org_uuid_invitations_uuid.py
calendly/models/operations/get_organizations_uuid_invitations.py
calendly/models/operations/get_organizations_uuid_memberships.py
calendly/models/operations/get_routing_form_submissions.py
calendly/models/operations/get_routing_form_submissions_uuid.py
calendly/models/operations/get_routing_forms_uuid.py
calendly/models/operations/get_scheduled_events_event_uuid_invitees_invitee_uuid.py
calendly/models/operations/get_scheduled_events_uuid.py
calendly/models/operations/get_users_user_uuid_webhooks_webhook_uuid.py
calendly/models/operations/geteventtypeavailabletimes.py
calendly/models/operations/getinviteenoshow.py
calendly/models/operations/getinvitees.py
calendly/models/operations/getuser.py
calendly/models/operations/getuseravailabilityschedules.py
calendly/models/operations/getuseravailabilityschedulesuuid.py
calendly/models/operations/getuserbusytimes.py
calendly/models/operations/list_activity_log.py
calendly/models/operations/list_organization_memberships.py
calendly/models/operations/list_routing_forms.py
calendly/models/operations/list_webhooks.py
calendly/models/operations/listeventtypes.py
calendly/models/operations/listscheduledevents.py
calendly/models/operations/me.py
calendly/models/operations/post_data_compliance_deletion_events.py
calendly_py-0.0.2.dist-info/LICENSE.md
calendly_py-0.0.2.dist-info/METADATA
calendly_py-0.0.2.dist-info/WHEEL
calendly_py-0.0.2.dist-info/top_level.txt
calendly_py-0.0.2.dist-info/RECORD
